setup.cfg
setup.py
XUDD.egg-info/PKG-INFO
XUDD.egg-info/SOURCES.txt
XUDD.egg-info/dependency_links.txt
XUDD.egg-info/top_level.txt
xudd/__init__.py
xudd/actor.py
xudd/hive.py
xudd/message.py
xudd/demos/__init__.py
xudd/demos/botherbotherbother.py
xudd/demos/lotsamessages.py
xudd/demos/robotscanner.py
xudd/tests/__init__.py
xudd/tests/test_messages.py