Metadata-Version: 1.0
Name: XUDD
Version: 0.1.0
Summary: An actor model system for python
Home-page: https://github.com/cwebber/xudd
Author: Christopher Allan Webber
Author-email: cwebber@dustycloud.org
License: UNKNOWN
Platform: UNKNOWN
